README
setup.py
bin/pf-server-list
bin/pf-server-role-add
bin/pf-server-start
bin/pf-server-terminate
bin/pf-server-upgrade
profab/__init__.py
profab/authentication.py
profab/connection.py
profab/ebs.py
profab/ec2.py
profab/main.py
profab/server.py
profab.egg-info/PKG-INFO
profab.egg-info/SOURCES.txt
profab.egg-info/dependency_links.txt
profab.egg-info/pbr.json
profab.egg-info/requires.txt
profab.egg-info/top_level.txt
profab/role/__init__.py
profab/role/bits.py
profab/role/eip.py
profab/role/postgres.py
profab/role/region.py
profab/role/security_group.py
profab/role/size.py
profab/role/smarthost.py
profab/role/wsgi.py
profab/role/ami/__init__.py
profab/role/ami/lucid.py
profab/role/ami/precise.py
profab/role/ami/trusty.py
profab/role/ami/ubuntu.py
profab/role/munin/__init__.py
profab/role/munin/templates.py