Metadata-Version: 1.1
Name: profab
Version: 0.5.1
Summary: Automated tools for engaging with server infrastructure on AWS
Home-page: https://github.com/Proteus-tech/profab
Author: Proteus Technologies Infrastructure team
Author-email: infrastructure@proteus-tech.com
License: Boost Software License - Version 1.0 - August 17th, 2003
Keywords: devops ec2 fabric boto ubuntu
Platform: UNKNOWN
Classifier: Development Status :: 3 - Alpha
Classifier: Intended Audience :: Developers
Classifier: Programming Language :: Python
Classifier: Topic :: Software Development :: Libraries :: Python Modules
Classifier: License :: OSI Approved
